robocore/__init__.py
robocore/analysis/__init__.py
robocore/analysis/singularity_analyzer.py
robocore/analysis/workspace_analyzer.py
robocore/configs/__init__.py
robocore/configs/config_manager.py
robocore/configs/schemas.py
robocore/kinematics/__init__.py
robocore/kinematics/bimanual.py
robocore/kinematics/fk.py
robocore/kinematics/ik.py
robocore/kinematics/jacobian.py
robocore/kinematics/task.py
robocore/kinematics/utils.py
robocore/kinematics/fk_utils/__init__.py
robocore/kinematics/fk_utils/bimanual_fk_solver_numpy.py
robocore/kinematics/fk_utils/bimanual_fk_solver_torch.py
robocore/kinematics/fk_utils/fk_solver_numpy.py
robocore/kinematics/fk_utils/fk_solver_torch.py
robocore/kinematics/ik_utils/__init__.py
robocore/kinematics/ik_utils/bimanual_ik_solver_numpy.py
robocore/kinematics/ik_utils/bimanual_ik_solver_torch.py
robocore/kinematics/ik_utils/ik_solver_numpy.py
robocore/kinematics/ik_utils/ik_solver_torch.py
robocore/kinematics/jacobian_utils/__init__.py
robocore/kinematics/jacobian_utils/bimanual_jacobian_solver_numpy.py
robocore/kinematics/jacobian_utils/bimanual_jacobian_solver_torch.py
robocore/kinematics/jacobian_utils/jacobian_solver_numpy.py
robocore/kinematics/jacobian_utils/jacobian_solver_torch.py
robocore/kinematics/solvers/__init__.py
robocore/kinematics/solvers/multi_chain_solver.py
robocore/modeling/__init__.py
robocore/modeling/robot_model.py
robocore/modeling/parser/__init__.py
robocore/modeling/parser/mjcf_parser.py
robocore/modeling/parser/urdf_parser.py
robocore/planning/__init__.py
robocore/planning/trajectory/__init__.py
robocore/planning/trajectory/cartesian_space.py
robocore/planning/trajectory/joint_space.py
robocore/planning/trajectory/velocity_profile.py
robocore/transform/__init__.py
robocore/transform/conversions.py
robocore/transform/se3.py
robocore/transform/so3.py
robocore/transform/utils.py
robocore/utils/__init__.py
robocore/utils/backend.py
robocore/utils/beauty_logger.py
robocore/utils/control_utils.py
synria_robocore-1.0.0.dist-info/licenses/LICENSE
synria_robocore-1.0.0.dist-info/METADATA
synria_robocore-1.0.0.dist-info/WHEEL
synria_robocore-1.0.0.dist-info/top_level.txt
synria_robocore-1.0.0.dist-info/RECORD
