Metadata-Version: 2.4
Name: synria-robocore
Version: 1.0.0
Summary: Unified High-Throughput Robotics Library
Home-page: https://github.com/Synria-Robotics/RoboCore
Author: Synria Robotics Team
Author-email: support@synriarobotics.ai
Classifier: Programming Language :: Python :: 3
Classifier: License :: OSI Approved :: GNU General Public License v3 (GPLv3)
Classifier: Operating System :: OS Independent
Classifier: Topic :: Scientific/Engineering :: Artificial Intelligence
Requires-Python: >=3.8
License-File: LICENSE
Requires-Dist: numpy>=1.21
Provides-Extra: torch
Requires-Dist: torch; extra == "torch"
Provides-Extra: mujoco
Requires-Dist: mujoco; extra == "mujoco"
Provides-Extra: dev
Requires-Dist: black; extra == "dev"
Requires-Dist: ruff; extra == "dev"
Requires-Dist: pytest; extra == "dev"
Requires-Dist: mypy; extra == "dev"
Dynamic: author
Dynamic: author-email
Dynamic: classifier
Dynamic: description
Dynamic: description-content-type
Dynamic: home-page
Dynamic: license-file
Dynamic: provides-extra
Dynamic: requires-dist
Dynamic: requires-python
Dynamic: summary
